my_package/__init__.py
cheigsfera-0.2.0.dist-info/METADATA
cheigsfera-0.2.0.dist-info/WHEEL
cheigsfera-0.2.0.dist-info/top_level.txt
cheigsfera-0.2.0.dist-info/RECORD
